math_kavin/__init__.py
math_kavin/basic_math.py
math_kavin-0.0.1.dist-info/License.txt
math_kavin-0.0.1.dist-info/METADATA
math_kavin-0.0.1.dist-info/WHEEL
math_kavin-0.0.1.dist-info/top_level.txt
math_kavin-0.0.1.dist-info/RECORD
